orpg/__init__.py
orpg/config.py
orpg/log.py
orpg/main.py
orpg/player_list.py
orpg/server_cli.py
orpg/version.py
orpg/chat/__init__.py
orpg/chat/chat_msg.py
orpg/chat/chat_util.py
orpg/chat/chat_version.py
orpg/chat/chatdisplay.py
orpg/chat/chatpanel.py
orpg/chat/chatwindow.py
orpg/chat/commands.py
orpg/chat/dice_tag.py
orpg/dieroller/__init__.py
orpg/dieroller/dicerolltab.py
orpg/dieroller/parser.py
orpg/gametree/__init__.py
orpg/gametree/gametree.py
orpg/gametree/gametree_version.py
orpg/gametree/icons.py
orpg/gametree/nodehandlers/__init__.py
orpg/gametree/nodehandlers/core.py
orpg/gametree/nodehandlers/flexi.py
orpg/images/icon_blank.png
orpg/images/icon_flexirpg.ico
orpg/images/icon_flexirpg.png
orpg/images/icon_gm.png
orpg/images/icon_lurker.png
orpg/images/icon_player.png
orpg/images/icon_typing.png
orpg/images/icons.xml
orpg/images/tool_add_mini.png
orpg/images/tool_bold.png
orpg/images/tool_circle.png
orpg/images/tool_color.png
orpg/images/tool_cone.png
orpg/images/tool_d10.png
orpg/images/tool_d100.png
orpg/images/tool_d12.png
orpg/images/tool_d20.png
orpg/images/tool_d4.png
orpg/images/tool_d6.png
orpg/images/tool_d8.png
orpg/images/tool_fog_add.png
orpg/images/tool_fog_enable.png
orpg/images/tool_fog_remove.png
orpg/images/tool_freehand.png
orpg/images/tool_italic.png
orpg/images/tool_line_width_1.png
orpg/images/tool_line_width_2.png
orpg/images/tool_line_width_4.png
orpg/images/tool_line_width_8.png
orpg/images/tool_mini_del.png
orpg/images/tool_mini_down.png
orpg/images/tool_mini_up.png
orpg/images/tool_more.png
orpg/images/tool_open.png
orpg/images/tool_polyline.png
orpg/images/tool_reset_view.png
orpg/images/tool_ruler.png
orpg/images/tool_save.png
orpg/images/tool_select.png
orpg/images/tool_text.png
orpg/images/tool_underline.png
orpg/images/tool_zoom_in.png
orpg/images/tool_zoom_out.png
orpg/images/tree_character.png
orpg/images/tree_default.png
orpg/images/tree_dice.png
orpg/images/tree_disabled.png
flexirpg-2.1.0.dist-info/LICENSE
flexirpg-2.1.0.dist-info/METADATA
flexirpg-2.1.0.dist-info/WHEEL
flexirpg-2.1.0.dist-info/entry_points.txt
flexirpg-2.1.0.dist-info/top_level.txt
flexirpg-2.1.0.dist-info/RECORD
